hello_pypi/__init__.py
hello_pypi/core.py
hello_pypi_thalles-0.1.0.dist-info/METADATA
hello_pypi_thalles-0.1.0.dist-info/WHEEL
hello_pypi_thalles-0.1.0.dist-info/top_level.txt
hello_pypi_thalles-0.1.0.dist-info/RECORD
