Metadata-Version: 2.4
Name: hello-pypi-thalles
Version: 0.1.0
Summary: A simple Hello World library example
Home-page: https://github.com/seuusuario/hello-pypi
Author: Thalles Freitas
Author-email: thalles@example.com
Classifier: Programming Language :: Python :: 3
Classifier: License :: OSI Approved :: MIT License
Classifier: Operating System :: OS Independent
Requires-Python: >=3.8
Dynamic: author
Dynamic: author-email
Dynamic: classifier
Dynamic: description
Dynamic: description-content-type
Dynamic: home-page
Dynamic: requires-python
Dynamic: summary
